akamaisdk/__init__.py
akamaisdk/appsec.py
akamaisdk/edgeauth.py
akamaisdk-0.1.0.dist-info/licenses/LICENSE
akamaisdk-0.1.0.dist-info/METADATA
akamaisdk-0.1.0.dist-info/WHEEL
akamaisdk-0.1.0.dist-info/top_level.txt
akamaisdk-0.1.0.dist-info/RECORD
