Metadata-Version: 2.4
Name: akamaisdk
Version: 0.1.0
Summary: Lightweight Python SDK for interacting with Akamai APIs using EdgeGrid authentication.
Author: Akamai
License: MIT License
Project-URL: Homepage, https://github.com/akamai-packages/akamaiapi
Project-URL: Documentation, https://akamai-packages.github.io/akamaiapi
Project-URL: Repository, https://github.com/akamai-packages/akamaiapi
Project-URL: Issues, https://github.com/akamai-packages/akamaiapi/issues
Requires-Python: >=3.7
License-File: LICENSE
Requires-Dist: requests
Dynamic: license-file
